[{"matchOptaId": "2w0wr7j0632bmrpnocgu3ufpw", "category": "CAF Champions league", "channelName": "beIN SPORTS 3", "channelExternalId": "94130ea17023c4837f0dcdda95034b65", "channelLogo": "https://prod-media.beinsports.com/image/94130ea17023c4837f0dcdda95034b65.png", "channelServers": "/refs/heads/main/channels-streaming-urls/bein-sports-3.json", "competitionName": "CAF Champions League", "competitionOptaId": "cse5oqqt2pzfcy8uz6yz3tkbj", "competitionLogo": "https://prod-media.beinsports.com/image/cse5oqqt2pzfcy8uz6yz3tkbj.png", "homeTeamOptaId": "5qei8eozbx70n6t11pr6rklsn", "homeTeamColor": "#2596be", "homeTeamfullName": "Al Hilal Omdurman", "homeTeamLogo": "https://prod-media.beinsports.com/image/5qei8eozbx70n6t11pr6rklsn.png", "awayTeamOptaId": "16245tyzivgxs6snosv45qbs5", "awayTeamColor": "#0e3cda", "awayTeamfullName": "Saint Eloi Lupopo", "awayTeamLogo": "https://prod-media.beinsports.com/image/16245tyzivgxs6snosv45qbs5.png", "round": "Regular Season", "matchDate": "2026-02-14Z", "matchTime": "13:00:00Z"}, {"matchOptaId": "2vn30o2yhsyydv56n00e31afo", "category": "CAF Champions league", "channelName": "beIN SPORTS 2", "channelExternalId": "94130ea17023c4837f0dcdda95034b65", "channelLogo": "https://prod-media.beinsports.com/image/4fbe073f17f161810fdf3dab1307b30f.png", "channelServers": "/refs/heads/main/channels-streaming-urls/bein-sports-2.json", "competitionName": "CAF Champions League", "competitionOptaId": "cse5oqqt2pzfcy8uz6yz3tkbj", "competitionLogo": "https://prod-media.beinsports.com/image/cse5oqqt2pzfcy8uz6yz3tkbj.png", "homeTeamOptaId": "3h2hc3qy5uritiscjfq27bv3a", "homeTeamColor": "#f6e601", "homeTeamfullName": "Mamelodi Sundowns", "homeTeamLogo": "https://prod-media.beinsports.com/image/3h2hc3qy5uritiscjfq27bv3a.png", "awayTeamOptaId": "3hjibr4pt10o0ifk7tbl7si6i", "awayTeamColor": "", "awayTeamfullName": "MC Alger", "awayTeamLogo": "https://prod-media.beinsports.com/image/3hjibr4pt10o0ifk7tbl7si6i.png", "round": "Regular Season", "matchDate": "2026-02-14Z", "matchTime": "13:00:00Z"}, {"matchOptaId": "2fc1kvignx7oybca1wqs2gsgk", "category": "Spanish League - Primera Divisi\u00f3n", "channelName": "beIN SPORTS 5", "channelExternalId": "94130ea17023c4837f0dcdda95034b65", "channelLogo": "https://prod-media.beinsports.com/image/0a5052334511e344f15ae0bfafd47a67.png", "channelServers": "/refs/heads/main/channels-streaming-urls/bein-sports-5.json", "competitionName": "La Liga", "competitionOptaId": "34pl8szyvrbwcmfkuocjm3r6t", "competitionLogo": "https://prod-media.beinsports.com/image/34pl8szyvrbwcmfkuocjm3r6t.png", "homeTeamOptaId": "c8llrezkm3b3op4afrou6b487", "homeTeamColor": "#0085CC", "homeTeamfullName": "Espanyol", "homeTeamLogo": "https://prod-media.beinsports.com/image/c8llrezkm3b3op4afrou6b487.png", "awayTeamOptaId": "6f27yvbqcngegwsg2ozxxdj4", "awayTeamColor": "#CCE9FF", "awayTeamfullName": "Celta de Vigo", "awayTeamLogo": "https://prod-media.beinsports.com/image/6f27yvbqcngegwsg2ozxxdj4.png", "round": "Regular Season", "matchDate": "2026-02-14Z", "matchTime": "13:00:00Z"}, {"matchOptaId": "3y1frwebei7qx893nmxk8pst0", "category": "Qatar Amir Cup", "channelName": "beIN SPORTS", "channelExternalId": "94130ea17023c4837f0dcdda95034b65", "channelLogo": "https://prod-media.beinsports.com/image/d78bded526b07ede88675c6412d63f3d.png", "channelServers": "/refs/heads/main/channels-streaming-urls/bein-sports.json", "competitionName": "Emir Cup", "competitionOptaId": "87p8k6unrouoedfe29qgnkshd", "competitionLogo": "https://prod-media.beinsports.com/image/87p8k6unrouoedfe29qgnkshd.png", "homeTeamOptaId": "1ermfibluk13kw936bhd4ts55", "homeTeamColor": "#fac705", "homeTeamfullName": "Al Gharafa", "homeTeamLogo": "https://prod-media.beinsports.com/image/1ermfibluk13kw936bhd4ts55.png", "awayTeamOptaId": "av9qqoh6iuwon6ib6v0bmejlk", "awayTeamColor": "", "awayTeamfullName": "Al Kharaitiyat", "awayTeamLogo": "https://prod-media.beinsports.com/image/av9qqoh6iuwon6ib6v0bmejlk.png", "round": "Regular Season", "matchDate": "2026-02-14Z", "matchTime": "13:30:00Z"}, {"matchOptaId": "cluz1thc2nuzlccn15e0yr28k", "category": "Football", "channelName": "beIN SPORTS 1", "channelExternalId": "94130ea17023c4837f0dcdda95034b65", "channelLogo": "https://prod-media.beinsports.com/image/f50c7035e532c49a0f6993d988e2e843.png", "channelServers": "/refs/heads/main/channels-streaming-urls/bein-sports-1.json", "competitionName": "FA Cup", "competitionOptaId": "2hj3286pqov1g1g59k2t2qcgm", "competitionLogo": "https://prod-media.beinsports.com/image/2hj3286pqov1g1g59k2t2qcgm.png", "homeTeamOptaId": "a3nyxabgsqlnqfkeg41m6tnpp", "homeTeamColor": "#1C2C5B", "homeTeamfullName": "Manchester City", "homeTeamLogo": "https://prod-media.beinsports.com/image/a3nyxabgsqlnqfkeg41m6tnpp.png", "awayTeamOptaId": "2dakjegmrc2cxx2hqq5wzegt", "awayTeamColor": "#000000", "awayTeamfullName": "Salford City", "awayTeamLogo": "https://prod-media.beinsports.com/image/2dakjegmrc2cxx2hqq5wzegt.png", "round": "Regular Season", "matchDate": "2026-02-14Z", "matchTime": "15:00:00Z"}, {"matchOptaId": "9a074ma6siuieqi65ifb30kd0", "category": "CAF Champions league", "channelName": "beIN SPORTS 2", "channelExternalId": "94130ea17023c4837f0dcdda95034b65", "channelLogo": "https://prod-media.beinsports.com/image/4fbe073f17f161810fdf3dab1307b30f.png", "channelServers": "/refs/heads/main/channels-streaming-urls/bein-sports-2.json", "competitionName": "CAF Champions League", "competitionOptaId": "cse5oqqt2pzfcy8uz6yz3tkbj", "competitionLogo": "https://prod-media.beinsports.com/image/cse5oqqt2pzfcy8uz6yz3tkbj.png", "homeTeamOptaId": "3s830ae09zdviu2cnqxixflq1", "homeTeamColor": "#ffc521", "homeTeamfullName": "ES Tunis", "homeTeamLogo": "https://prod-media.beinsports.com/image/3s830ae09zdviu2cnqxixflq1.png", "awayTeamOptaId": "a29xzt037ts7jcubdkm0gzqns", "awayTeamColor": "#ffe900", "awayTeamfullName": "Petro de Luanda", "awayTeamLogo": "https://prod-media.beinsports.com/image/a29xzt037ts7jcubdkm0gzqns.png", "round": "Regular Season", "matchDate": "2026-02-14Z", "matchTime": "16:00:00Z"}, {"matchOptaId": "92w3v1zmovn1e6fdahj11l5w4", "category": "French League - Ligue 1", "channelName": "beIN SPORTS 4", "channelExternalId": "94130ea17023c4837f0dcdda95034b65", "channelLogo": "https://prod-media.beinsports.com/image/e92b755eb0d8800175a02a35c2bf44fe.png", "channelServers": "/refs/heads/main/channels-streaming-urls/bein-sports-4.json", "competitionName": "Ligue 1", "competitionOptaId": "dm5ka0os1e3dxcp3vh05kmp33", "competitionLogo": "https://prod-media.beinsports.com/image/dm5ka0os1e3dxcp3vh05kmp33.png", "homeTeamOptaId": "27xvwccz8kpmqsefjv2b2sc0o", "homeTeamColor": "#CBF4FF", "homeTeamfullName": "Olympique Marseille", "homeTeamLogo": "https://prod-media.beinsports.com/image/27xvwccz8kpmqsefjv2b2sc0o.png", "awayTeamOptaId": "71ajatxnuhc5cnm3xvgdky49w", "awayTeamColor": "#009fe3", "awayTeamfullName": "Strasbourg", "awayTeamLogo": "https://prod-media.beinsports.com/image/71ajatxnuhc5cnm3xvgdky49w.png", "round": "Regular Season", "matchDate": "2026-02-14Z", "matchTime": "16:00:00Z"}, {"matchOptaId": "75ubiylrgy4wjyoqhw51o58gk", "category": "CAF Confederation Cup", "channelName": "beIN SPORTS 3", "channelExternalId": "94130ea17023c4837f0dcdda95034b65", "channelLogo": "https://prod-media.beinsports.com/image/94130ea17023c4837f0dcdda95034b65.png", "channelServers": "/refs/heads/main/channels-streaming-urls/bein-sports-3.json", "competitionName": "CAF Confederation Cup", "competitionOptaId": "bx57cmq1edfq53ckfk791supi", "competitionLogo": "https://prod-media.beinsports.com/image/bx57cmq1edfq53ckfk791supi.png", "homeTeamOptaId": "2c1lvho9eqtqfqf4t3cv0f237", "homeTeamColor": "#ffffff", "homeTeamfullName": "Zamalek", "homeTeamLogo": "https://prod-media.beinsports.com/image/2c1lvho9eqtqfqf4t3cv0f237.png", "awayTeamOptaId": "9g72y015b6fgkgtpx1c67qemi", "awayTeamColor": "", "awayTeamfullName": "Kaizer Chiefs", "awayTeamLogo": "https://prod-media.beinsports.com/image/9g72y015b6fgkgtpx1c67qemi.png", "round": "Regular Season", "matchDate": "2026-02-14Z", "matchTime": "16:00:00Z"}, {"matchOptaId": "3ya5vah5egvrp6dxn7rwbjjtg", "category": "Qatar Amir Cup", "channelName": "beIN SPORTS", "channelExternalId": "94130ea17023c4837f0dcdda95034b65", "channelLogo": "https://prod-media.beinsports.com/image/d78bded526b07ede88675c6412d63f3d.png", "channelServers": "/refs/heads/main/channels-streaming-urls/bein-sports.json", "competitionName": "Emir Cup", "competitionOptaId": "87p8k6unrouoedfe29qgnkshd", "competitionLogo": "https://prod-media.beinsports.com/image/87p8k6unrouoedfe29qgnkshd.png", "homeTeamOptaId": "bysx5682cx93z7yvefajzdban", "homeTeamColor": "#ee2633", "homeTeamfullName": "Al Rayyan", "homeTeamLogo": "https://prod-media.beinsports.com/image/bysx5682cx93z7yvefajzdban.png", "awayTeamOptaId": "8d05m2jwv1yi996seuz3py54t", "awayTeamColor": "", "awayTeamfullName": "Al Khor", "awayTeamLogo": "https://prod-media.beinsports.com/image/8d05m2jwv1yi996seuz3py54t.png", "round": "Regular Season", "matchDate": "2026-02-14Z", "matchTime": "16:15:00Z"}, {"matchOptaId": "ark96hyihyvok7y6wrosdyadw", "category": "Football", "channelName": "beIN SPORTS 1", "channelExternalId": "94130ea17023c4837f0dcdda95034b65", "channelLogo": "https://prod-media.beinsports.com/image/f50c7035e532c49a0f6993d988e2e843.png", "channelServers": "/refs/heads/main/channels-streaming-urls/bein-sports-1.json", "competitionName": "FA Cup", "competitionOptaId": "2hj3286pqov1g1g59k2t2qcgm", "competitionLogo": "https://prod-media.beinsports.com/image/2hj3286pqov1g1g59k2t2qcgm.png", "homeTeamOptaId": "b496gs285it6bheuikox6z9mj", "homeTeamColor": "#ffe500", "homeTeamfullName": "Aston Villa", "homeTeamLogo": "https://prod-media.beinsports.com/image/b496gs285it6bheuikox6z9mj.png", "awayTeamOptaId": "7vn2i2kd35zuetw6b38gw9jsz", "awayTeamColor": "#172F55", "awayTeamfullName": "Newcastle United", "awayTeamLogo": "https://prod-media.beinsports.com/image/7vn2i2kd35zuetw6b38gw9jsz.png", "round": "Regular Season", "matchDate": "2026-02-14Z", "matchTime": "17:45:00Z"}, {"matchOptaId": "939i2u1dqhrqht2dk192oanmc", "category": "French League - Ligue 1", "channelName": "beIN SPORTS 8", "channelExternalId": "94130ea17023c4837f0dcdda95034b65", "channelLogo": "https://prod-media.beinsports.com/image/a9dd7e3c6ee87a48cb35b729caf61eb5.png", "channelServers": "/refs/heads/main/channels-streaming-urls/bein-sports-8.json", "competitionName": "Ligue 1", "competitionOptaId": "dm5ka0os1e3dxcp3vh05kmp33", "competitionLogo": "https://prod-media.beinsports.com/image/dm5ka0os1e3dxcp3vh05kmp33.png", "homeTeamOptaId": "be2k34rut1lz79jxenabttqlc", "homeTeamColor": "#494596", "homeTeamfullName": "Lille", "homeTeamLogo": "https://prod-media.beinsports.com/image/be2k34rut1lz79jxenabttqlc.png", "awayTeamOptaId": "3adj8hkws0z1al232bg2h6tk0", "awayTeamColor": "#5E0404", "awayTeamfullName": "Brest", "awayTeamLogo": "https://prod-media.beinsports.com/image/3adj8hkws0z1al232bg2h6tk0.png", "round": "Regular Season", "matchDate": "2026-02-14Z", "matchTime": "18:00:00Z"}, {"matchOptaId": "cn3rdr4i0py28pse63t4dhiqc", "category": "CAF Champions league", "channelName": "beIN SPORTS 5", "channelExternalId": "94130ea17023c4837f0dcdda95034b65", "channelLogo": "https://prod-media.beinsports.com/image/0a5052334511e344f15ae0bfafd47a67.png", "channelServers": "/refs/heads/main/channels-streaming-urls/bein-sports-5.json", "competitionName": "CAF Champions League", "competitionOptaId": "cse5oqqt2pzfcy8uz6yz3tkbj", "competitionLogo": "https://prod-media.beinsports.com/image/cse5oqqt2pzfcy8uz6yz3tkbj.png", "homeTeamOptaId": "5iuuccvbznfqyibcx96knhysc", "homeTeamColor": "#fe5f01", "homeTeamfullName": "RSB Berkane", "homeTeamLogo": "https://prod-media.beinsports.com/image/5iuuccvbznfqyibcx96knhysc.png", "awayTeamOptaId": "aqg0pzg5bs6wizwkjl6wkjnc9", "awayTeamColor": "#ebf9fe", "awayTeamfullName": "Rivers United", "awayTeamLogo": "https://prod-media.beinsports.com/image/aqg0pzg5bs6wizwkjl6wkjnc9.png", "round": "Regular Season", "matchDate": "2026-02-14Z", "matchTime": "19:00:00Z"}, {"matchOptaId": "95hg76d9v54mx9ve9t87qv5zo", "category": "Handball - French Handball League", "channelName": "beIN SPORTS", "channelExternalId": "94130ea17023c4837f0dcdda95034b65", "channelLogo": "https://prod-media.beinsports.com/image/d78bded526b07ede88675c6412d63f3d.png", "channelServers": "/refs/heads/main/channels-streaming-urls/bein-sports.json", "competitionName": "Ligue 1", "competitionOptaId": "dm5ka0os1e3dxcp3vh05kmp33", "competitionLogo": "https://prod-media.beinsports.com/image/dm5ka0os1e3dxcp3vh05kmp33.png", "homeTeamOptaId": "z1wbqtd0fz5t5eezjvrbld3h", "homeTeamColor": "#e13327", "homeTeamfullName": "Rennes", "homeTeamLogo": "https://prod-media.beinsports.com/image/z1wbqtd0fz5t5eezjvrbld3h.png", "awayTeamOptaId": "2b3mar72yy8d6uvat1ka6tn3r", "awayTeamColor": "#004170", "awayTeamfullName": "Paris Saint-Germain", "awayTeamLogo": "https://prod-media.beinsports.com/image/2b3mar72yy8d6uvat1ka6tn3r.png", "round": "Regular Season", "matchDate": "2026-02-13Z", "matchTime": "18:00:00Z"}, {"matchOptaId": "56ur4hqxvfvrader9d16getqs", "category": "CAF Confederation Cup", "channelName": "beIN SPORTS 3", "channelExternalId": "94130ea17023c4837f0dcdda95034b65", "channelLogo": "https://prod-media.beinsports.com/image/94130ea17023c4837f0dcdda95034b65.png", "channelServers": "/refs/heads/main/channels-streaming-urls/bein-sports-3.json", "competitionName": "CAF Confederation Cup", "competitionOptaId": "bx57cmq1edfq53ckfk791supi", "competitionLogo": "https://prod-media.beinsports.com/image/bx57cmq1edfq53ckfk791supi.png", "homeTeamOptaId": "8yto6v12sv1yrpg8ad5eaq62c", "homeTeamColor": "#a30b13", "homeTeamfullName": "USM Alger", "homeTeamLogo": "https://prod-media.beinsports.com/image/8yto6v12sv1yrpg8ad5eaq62c.png", "awayTeamOptaId": "bfmfxajo833u9t76ol1glbf8l", "awayTeamColor": "", "awayTeamfullName": "Olympic Safi", "awayTeamLogo": "https://prod-media.beinsports.com/image/bfmfxajo833u9t76ol1glbf8l.png", "round": "Regular Season", "matchDate": "2026-02-14Z", "matchTime": "19:00:00Z"}, {"matchOptaId": "2gtyyqnsw87ojqc60b9b50dn8", "category": "Spanish League - Primera Divisi\u00f3n", "channelName": "beIN SPORTS 2", "channelExternalId": "94130ea17023c4837f0dcdda95034b65", "channelLogo": "https://prod-media.beinsports.com/image/4fbe073f17f161810fdf3dab1307b30f.png", "channelServers": "/refs/heads/main/channels-streaming-urls/bein-sports-2.json", "competitionName": "La Liga", "competitionOptaId": "34pl8szyvrbwcmfkuocjm3r6t", "competitionLogo": "https://prod-media.beinsports.com/image/34pl8szyvrbwcmfkuocjm3r6t.png", "homeTeamOptaId": "3kq9cckrnlogidldtdie2fkbl", "homeTeamColor": "#fcbf00", "homeTeamfullName": "Real Madrid", "homeTeamLogo": "https://prod-media.beinsports.com/image/3kq9cckrnlogidldtdie2fkbl.png", "awayTeamOptaId": "63f5h8t5e9qm1fqmvfkb23ghh", "awayTeamColor": "#143c8b", "awayTeamfullName": "Real Sociedad", "awayTeamLogo": "https://prod-media.beinsports.com/image/63f5h8t5e9qm1fqmvfkb23ghh.png", "round": "Regular Season", "matchDate": "2026-02-14Z", "matchTime": "20:00:00Z"}, {"matchOptaId": "2kfrupbo18nzx1c07s506vv9w", "category": "Football", "channelName": "beIN SPORTS 1", "channelExternalId": "94130ea17023c4837f0dcdda95034b65", "channelLogo": "https://prod-media.beinsports.com/image/f50c7035e532c49a0f6993d988e2e843.png", "channelServers": "/refs/heads/main/channels-streaming-urls/bein-sports-1.json", "competitionName": "FA Cup", "competitionOptaId": "2hj3286pqov1g1g59k2t2qcgm", "competitionLogo": "https://prod-media.beinsports.com/image/2hj3286pqov1g1g59k2t2qcgm.png", "homeTeamOptaId": "c8h9bw1l82s06h77xxrelzhur", "homeTeamColor": "#DFE4DF", "homeTeamfullName": "Liverpool", "homeTeamLogo": "https://prod-media.beinsports.com/image/c8h9bw1l82s06h77xxrelzhur.png", "awayTeamOptaId": "e5p0ehyguld7egzhiedpdnc3w", "awayTeamColor": "#005daa", "awayTeamfullName": "Brighton & Hove Albion", "awayTeamLogo": "https://prod-media.beinsports.com/image/e5p0ehyguld7egzhiedpdnc3w.png", "round": "Regular Season", "matchDate": "2026-02-14Z", "matchTime": "20:00:00Z"}, {"matchOptaId": "9542olzreg98t5g7iy5689yc4", "category": "French League - Ligue 1", "channelName": "beIN SPORTS 4", "channelExternalId": "94130ea17023c4837f0dcdda95034b65", "channelLogo": "https://prod-media.beinsports.com/image/e92b755eb0d8800175a02a35c2bf44fe.png", "channelServers": "/refs/heads/main/channels-streaming-urls/bein-sports-4.json", "competitionName": "Ligue 1", "competitionOptaId": "dm5ka0os1e3dxcp3vh05kmp33", "competitionLogo": "https://prod-media.beinsports.com/image/dm5ka0os1e3dxcp3vh05kmp33.png", "homeTeamOptaId": "8v00fx2zwhiwm05tqqkt122p5", "homeTeamColor": "#0A0F2C", "homeTeamfullName": "Paris FC", "homeTeamLogo": "https://prod-media.beinsports.com/image/8v00fx2zwhiwm05tqqkt122p5.png", "awayTeamOptaId": "3xedluek08t2ka7oypwuullcn", "awayTeamColor": "#ee161f", "awayTeamfullName": "Lens", "awayTeamLogo": "https://prod-media.beinsports.com/image/3xedluek08t2ka7oypwuullcn.png", "round": "Regular Season", "matchDate": "2026-02-14Z", "matchTime": "20:05:00Z"}]